davidkhala/spark/__init__.py
davidkhala/spark/connect/__init__.py
davidkhala/spark/connect/stream.py
davidkhala/spark/context.py
davidkhala/spark/df.py
davidkhala/spark/graph/__init__.py
davidkhala/spark/session.py
davidkhala/spark/sink/__init__.py
davidkhala/spark/sink/file.py
davidkhala/spark/sink/jdbc.py
davidkhala/spark/sink/stream/__init__.py
davidkhala/spark/sink/stream/vendor.py
davidkhala/spark/source/__init__.py
davidkhala/spark/source/file.py
davidkhala/spark/source/stream/__init__.py
davidkhala_spark-0.1.3.dist-info/METADATA
davidkhala_spark-0.1.3.dist-info/WHEEL
davidkhala_spark-0.1.3.dist-info/RECORD
